{"project":"platform/core/multimedia/libmm-imgp-gstcs","branch":"tizen","id":"I8b019229739a1256129e29bb7bcac682eb9fd9f8","number":"31275","subject":"Removed redundant checks in the if statement. These checks are already done in the same if","owner":{"name":"Sanjay Narasimha Murthy","email":"sanjay.nm@samsung.com","username":"sanjaynm"},"url":"https://review.tizen.org/gerrit/31275","commitMessage":"Removed redundant checks in the if statement. These checks are already done in the same if\n\nChange-Id: I8b019229739a1256129e29bb7bcac682eb9fd9f8\nSigned-off-by: Sanjay NM \u003csanjay.nm@samsung.com\u003e\n","createdOn":1417607328,"lastUpdated":1417607328,"sortKey":"0031898400007a2b","open":true,"status":"NEW","comments":[{"timestamp":1417607328,"reviewer":{"name":"Sanjay Narasimha Murthy","email":"sanjay.nm@samsung.com","username":"sanjaynm"},"message":"Uploaded patch set 1."}]}
{"project":"platform/core/multimedia/libmm-imgp-gstcs","branch":"tizen","id":"Iddc3b8a1dfb44110819975fb0231e5460ce1b2d8","number":"30808","subject":"Remove duplicate condition in _mm_gst_can_resize_format()","owner":{"name":"Ravi kiran K N","email":"ravi.kiran@samsung.com","username":"ravikirankn"},"url":"https://review.tizen.org/gerrit/30808","commitMessage":"Remove duplicate condition in _mm_gst_can_resize_format()\n\nstrcmp(__format_label, \"Y800\") and strcmp(__format_label, \"UYVY\") checks\nappear twice. Remove the redundant checking.\n\nChange-Id: Iddc3b8a1dfb44110819975fb0231e5460ce1b2d8\nSigned-off-by: Ravi Kiran K N \u003cravi.kiran@samsung.com\u003e\n","createdOn":1416914289,"lastUpdated":1416914289,"sortKey":"00315c6600007858","open":true,"status":"NEW","comments":[{"timestamp":1416914289,"reviewer":{"name":"Ravi kiran K N","email":"ravi.kiran@samsung.com","username":"ravikirankn"},"message":"Uploaded patch set 1."}]}
