{"project":"platform/core/system/libLogger","branch":"tizen","id":"I4abe68e9631e7621d9c41192d3634eaedd823ab3","number":"32380","subject":"Add LoggerScope object for better debugging","owner":{"name":"Lukasz Kostyra","email":"l.kostyra@samsung.com","username":"lkostyra11"},"url":"https://review.tizen.org/gerrit/32380","commitMessage":"Add LoggerScope object for better debugging\n\n[Feature]       New LoggerScope object.\n[Cause]         Need to have automatic messages generated when entering\n                or leaving scopes\n[Solution]      Add new LoggerScope object for scope debugging\n[Verification]  Build, install\n\nChange-Id: I4abe68e9631e7621d9c41192d3634eaedd823ab3\n","createdOn":1418823298,"lastUpdated":1420208515,"sortKey":"003232dd00007e7c","open":true,"status":"NEW","comments":[{"timestamp":1418823298,"reviewer":{"name":"Lukasz Kostyra","email":"l.kostyra@samsung.com","username":"lkostyra11"},"message":"Uploaded patch set 1."},{"timestamp":1418823650,"reviewer":{"name":"Build Bot","email":"b.bot@partner.samsung.com","username":"bbot"},"message":"Patch Set 1: Code-Review+1\n\nBuild Successful"},{"timestamp":1418827940,"reviewer":{"name":"Piotr Bartosiewicz","email":"p.bartosiewi@partner.samsung.com","username":"pbartosiewi"},"message":"Patch Set 1: Code-Review-1\n\n(2 comments)"},{"timestamp":1418998582,"reviewer":{"name":"Jan Olszak","email":"j.olszak@samsung.com","username":"jolszak"},"message":"Patch Set 1: Code-Review-1\n\n(1 comment)"},{"timestamp":1420198614,"reviewer":{"name":"Lukasz Kostyra","email":"l.kostyra@samsung.com","username":"lkostyra11"},"message":"Uploaded patch set 2."},{"timestamp":1420198640,"reviewer":{"name":"Lukasz Kostyra","email":"l.kostyra@samsung.com","username":"lkostyra11"},"message":"Patch Set 1:\n\n(3 comments)"},{"timestamp":1420198710,"reviewer":{"name":"Build Bot","email":"b.bot@partner.samsung.com","username":"bbot"},"message":"Patch Set 2: Code-Review+1\n\nBuild Successful"},{"timestamp":1420208515,"reviewer":{"name":"Jan Olszak","email":"j.olszak@samsung.com","username":"jolszak"},"message":"Patch Set 2: Code-Review-1\n\n(1 comment)"}]}
