{"project":"pre-built/toolchain-x86","branch":"tizen_mobile","id":"Idcb5b3f442f3c92b65007fb4aa07b1604bef6f37","number":"33407","subject":"Update mobile x86 toolchain according to latest snapshot repo","owner":{"name":"Li Jinjing","username":"jinjingx"},"url":"https://review.tizen.org/gerrit/33407","commitMessage":"Update mobile x86 toolchain according to latest snapshot repo\n\nhttps://download.tizen.org/snapshots/tizen/mobile/tizen-mobile_20150109.2/\n\nKey updates are:\n\nrpm-4.11.0.1-24.2.i686.rpm -\u003e rpm-4.11.0.1-26.1.i686.rpm\nrpm-build-4.11.0.1-24.2.i686.rpm -\u003e rpm-build-4.11.0.1-26.1.i686.rpm\nrpm-devel-4.11.0.1-24.2.i686.rpm -\u003e rpm-devel-4.11.0.1-26.1.i686.rpm\nrpm-security-plugin-4.11.0.1-24.2.i686.rpm -\u003e\nrpm-security-plugin-4.11.0.1-26.1.i686.rpm\n\nChange-Id: Idcb5b3f442f3c92b65007fb4aa07b1604bef6f37\nSigned-off-by: Li Jinjing \u003cjinjingx.li@intel.com\u003e\n","createdOn":1420783596,"lastUpdated":1420783596,"sortKey":"0032584e0000827f","open":true,"status":"NEW","comments":[{"timestamp":1420783596,"reviewer":{"name":"Li Jinjing","username":"jinjingx"},"message":"Uploaded patch set 1."}]}
{"project":"pre-built/toolchain-x86","branch":"tizen_ivi","id":"I55d5548375f3409e2e76ef56168a12d4462d4375","number":"21663","subject":"just for testing permission","owner":{"name":"Qiang Zhang","email":"qiang.z.zhang@intel.com","username":"xiaoqiang"},"url":"https://review.tizen.org/gerrit/21663","commitMessage":"just for testing permission\n\nChange-Id: I55d5548375f3409e2e76ef56168a12d4462d4375\nSigned-off-by: Zhang Qiang \u003cqiang.z.zhang@intel.com\u003e\n","createdOn":1401087600,"lastUpdated":1401087600,"sortKey":"002d56040000549f","open":true,"status":"NEW","comments":[{"timestamp":1401087600,"reviewer":{"name":"Qiang Zhang","email":"qiang.z.zhang@intel.com","username":"xiaoqiang"},"message":"Uploaded patch set 1."}]}
{"project":"pre-built/toolchain-x86","branch":"tizen_ivi","id":"I5a3f22158742c6486be03c807dfcd063aec82926","number":"20966","subject":"add bzip2-devel for circle","owner":{"name":"yigang wen","username":"yigangwx"},"url":"https://review.tizen.org/gerrit/20966","commitMessage":"add bzip2-devel for circle\n\ndepanneur won\u0027t find circle libtool-\u003etexinfo-\u003ebzip2 without bzip2-devel\n\nChange-Id: I5a3f22158742c6486be03c807dfcd063aec82926\nSigned-off-by: Yigang Wen \u003cyigangx.wen@intel.com\u003e\n","createdOn":1400057521,"lastUpdated":1400057521,"sortKey":"002d12f4000051e6","open":true,"status":"NEW","comments":[{"timestamp":1400057521,"reviewer":{"name":"yigang wen","username":"yigangwx"},"message":"Uploaded patch set 1."}]}
