{"project":"framework/api/calendar","branch":"master","id":"I6d5a5230487644957ac52c689af2395c3267338a","number":"1797","subject":"2.0_alpha release commit","owner":{"name":"Jang Yeongil","username":"biskett"},"url":"https://review.tizen.org/gerrit/1797","commitMessage":"2.0_alpha release commit\n","createdOn":1348179138,"lastUpdated":1348179241,"sortKey":"001fdfd200000705","open":false,"status":"MERGED","comments":[{"timestamp":1348179240,"reviewer":{"name":"Hotae Kim","email":"hotae.kim@samsung.com","username":"hotae"},"message":"Patch Set 1: Verified; Looks good to me, approved\n\n"},{"timestamp":1348179241,"reviewer":{"name":"Hotae Kim","email":"hotae.kim@samsung.com","username":"hotae"},"message":"Change has been successfully merged into the git repository."}]}
